slack_proxy_server/__init__.py
slack_proxy_server/slack_proxy_server.py
slack_proxy_server-0.1.1.data/scripts/run_slack_proxy_server.sh
slack_proxy_server-0.1.1.dist-info/AUTHORS.rst
slack_proxy_server-0.1.1.dist-info/LICENSE
slack_proxy_server-0.1.1.dist-info/METADATA
slack_proxy_server-0.1.1.dist-info/WHEEL
slack_proxy_server-0.1.1.dist-info/top_level.txt
slack_proxy_server-0.1.1.dist-info/RECORD
