Metadata-Version: 2.1
Name: slack-proxy-server
Version: 0.1.1
Summary: Slack Proxy Server
Home-page: https://bitbucket.org/yujinrobot/slack_proxy_server
Author: SimJoonYeol
Author-email: jysim@yujinrobot.com
License: MIT license
Keywords: slack_proxy_server
Platform: UNKNOWN
Classifier: Development Status :: 2 - Pre-Alpha
Classifier: Intended Audience :: Developers
Classifier: License :: OSI Approved :: MIT License
Classifier: Natural Language :: English
Classifier: Programming Language :: Python :: 3.6
Classifier: Programming Language :: Python :: 3.7
Requires-Dist: pyyaml (==5.1.2)
Requires-Dist: slackclient
Requires-Dist: sanic
Requires-Dist: sanic-cors
